stanley_cbp/Stanley_Analysis_InterpN.py
stanley_cbp/Stanley_Constants.py
stanley_cbp/Stanley_Detrending.py
stanley_cbp/Stanley_Functions.py
stanley_cbp/Stanley_PlanetSearch_InterpN_DebugPadding.py
stanley_cbp/Stanley_TransitTiming.py
stanley_cbp/__init__.py
stanley_cbp/Databases/ANTIC_Catalogue_12_11_filtered.csv
stanley_cbp/Databases/__init__.py
stanley_cbp/Databases/common_false_positives.csv
stanley_cbp/Databases/eblm_master_table.csv
stanley_cbp/Databases/exoplanet_archive.csv
stanley_cbp/Databases/villanova_orbit_data_kepler.csv
stanley_cbp/Databases/villanova_orbit_data_tess.csv
stanley_cbp/Databases/windemuth_stellar_data.csv
stanley_cbp/Databases/SpecificTargetCuts/10198109_manual_cuts.csv
stanley_cbp/Databases/SpecificTargetCuts/1026032_manual_cuts.csv
stanley_cbp/Databases/SpecificTargetCuts/10352603_manual_cuts.csv
stanley_cbp/Databases/SpecificTargetCuts/12217907_manual_cuts.csv
stanley_cbp/Databases/SpecificTargetCuts/12251779_manual_cuts.csv
stanley_cbp/Databases/SpecificTargetCuts/12644769_manual_cuts.csv
stanley_cbp/Databases/SpecificTargetCuts/4839180_manual_cuts.csv
stanley_cbp/Databases/SpecificTargetCuts/5473556_manual_cuts.csv
stanley_cbp/Databases/SpecificTargetCuts/5622250_manual_cuts.csv
stanley_cbp/Databases/SpecificTargetCuts/6233903_manual_cuts.csv
stanley_cbp/Databases/SpecificTargetCuts/6421188_manual_cuts.csv
stanley_cbp/Databases/SpecificTargetCuts/6522750_manual_cuts.csv
stanley_cbp/Databases/SpecificTargetCuts/6523216_manual_cuts.csv
stanley_cbp/Databases/SpecificTargetCuts/6672229_manual_cuts.csv
stanley_cbp/Databases/SpecificTargetCuts/6762829_manual_cuts.csv
stanley_cbp/Databases/SpecificTargetCuts/7121885_manual_cuts.csv
stanley_cbp/Databases/SpecificTargetCuts/7122259_manual_cuts.csv
stanley_cbp/Databases/SpecificTargetCuts/7670617_manual_cuts.csv
stanley_cbp/Databases/SpecificTargetCuts/7767733_manual_cuts.csv
stanley_cbp/Databases/SpecificTargetCuts/8023317_manual_cuts.csv
stanley_cbp-0.1.79.dist-info/licenses/License.txt
stanley_cbp-0.1.79.dist-info/METADATA
stanley_cbp-0.1.79.dist-info/WHEEL
stanley_cbp-0.1.79.dist-info/top_level.txt
stanley_cbp-0.1.79.dist-info/RECORD
