Metadata-Version: 2.4
Name: stanley_cbp
Version: 0.1.79
Summary: Algorithm developed to conduct a systematic search for exoplanets orbiting eclipsing binary stars.
Author-email: David Martin <David.Martin@tufts.edu>, "Chanita (Wata) Tubthong" <Chanita.Tubthong@tufts.edu>, Tess Kleanthous <Tess.Kleanthous@tufts.edu>
License: MIT License
Requires-Python: >=3.9
License-File: License.txt
Requires-Dist: numpy>=1.22
Requires-Dist: scipy>=1.10
Requires-Dist: pandas>=1.5
Requires-Dist: matplotlib>=3.7
Requires-Dist: astropy>=5.0
Requires-Dist: astroquery>=0.4
Requires-Dist: lightkurve>=2.4
Requires-Dist: batman-package>=2.4
Requires-Dist: rebound>=4.4
Requires-Dist: wotan<2.0,>=1.10
Requires-Dist: PyAstronomy>=0.18
Requires-Dist: ldtk>=1.3
Requires-Dist: ipython>=8.0
Dynamic: license-file
